occ/__init__.py
occ/main.py
occ/controllers/__init__.py
occ/controllers/base.py
occ/controllers/loadbalancer.py
occ/core/__init__.py
occ/core/exc.py
occ/core/version.py
occ/ext/__init__.py
occ/plugins/__init__.py
occ/templates/__init__.py
occ/templates/command1.jinja2
occ-0.0.2.dev20190912195130.dist-info/LICENSE.md
occ-0.0.2.dev20190912195130.dist-info/METADATA
occ-0.0.2.dev20190912195130.dist-info/WHEEL
occ-0.0.2.dev20190912195130.dist-info/entry_points.txt
occ-0.0.2.dev20190912195130.dist-info/top_level.txt
occ-0.0.2.dev20190912195130.dist-info/RECORD
