Metadata-Version: 2.1
Name: occ
Version: 0.0.2.dev20190912195130
Summary: Octavia Chicken Checker looks for abandoned Octavia load balancer artifacts, amphoras, and so forth. Optionally it will clean them up as well.
Home-page: http://github.com/bunchc/octvia_chicken_checker/
Author: Cody Bunch
Author-email: cody.bunch@rackspace.com
License: UNKNOWN
Platform: UNKNOWN
Classifier: Development Status :: 3 - Alpha
Classifier: Programming Language :: Python :: 3
